fastBio/__init__.py
fastBio/data.py
fastBio/distributed.py
fastBio/iterators.py
fastBio/learner.py
fastBio/models.py
fastBio/transform.py
fastBio-0.1.7.dist-info/LICENSE
fastBio-0.1.7.dist-info/METADATA
fastBio-0.1.7.dist-info/WHEEL
fastBio-0.1.7.dist-info/top_level.txt
fastBio-0.1.7.dist-info/RECORD
