Metadata-Version: 2.1
Name: fastBio
Version: 0.1.7
Summary: Deep learning for biological sequences with fastai
Home-page: https://github.com/ahoarfrost/fastBio
Author: Adrienne Hoarfrost
Author-email: adrienne.l.hoarfrost@gmail.com
License: UNKNOWN
Platform: UNKNOWN
Classifier: Programming Language :: Python :: 3
Classifier: License :: OSI Approved :: MIT License
Classifier: Operating System :: OS Independent
Requires-Python: >=3.6
Requires-Dist: fastai (==1.0.52)
Requires-Dist: biopython (==1.73)
Requires-Dist: torch (==1.2.0)
Requires-Dist: torchvision (==0.4.0)
